{"name":"rax-redis","description":"wrapper cookbook for redis heat deployment","long_description":"# rax-redis cookbook\n\n# Requirements\n\n# Usage\n\n# Attributes\n\n# Recipes\n\n# Author\n\nAuthor:: Jason Boyles (<jason.boyles@rackspace.com>)\n","maintainer":"Jason Boyles","maintainer_email":"jason.boyles@rackspace.com","license":"All rights reserved","platforms":{},"dependencies":{"redisio":">= 0.0.0","apt":">= 0.0.0","build-essential":">= 0.0.0"},"recommendations":{},"suggestions":{},"conflicting":{},"providing":{},"replacing":{},"attributes":{},"groupings":{},"recipes":{},"version":"0.1.0"}